MANIFEST.in
README.rst
setup.cfg
setup.py
collective/__init__.py
collective.sliderfields.egg-info/PKG-INFO
collective.sliderfields.egg-info/SOURCES.txt
collective.sliderfields.egg-info/dependency_links.txt
collective.sliderfields.egg-info/entry_points.txt
collective.sliderfields.egg-info/namespace_packages.txt
collective.sliderfields.egg-info/not-zip-safe
collective.sliderfields.egg-info/paster_plugins.txt
collective.sliderfields.egg-info/requires.txt
collective.sliderfields.egg-info/top_level.txt
collective/sliderfields/__init__.py
collective/sliderfields/configure.zcml
collective/sliderfields/interfaces.py
collective/sliderfields/setuphandlers.py
collective/sliderfields/behavior/README.txt
collective/sliderfields/behavior/__init__.py
collective/sliderfields/behavior/configure.zcml
collective/sliderfields/behavior/sliderimage.py
collective/sliderfields/browser/README.txt
collective/sliderfields/browser/__init__.py
collective/sliderfields/content/README.txt
collective/sliderfields/content/__init__.py
collective/sliderfields/locales/README.txt
collective/sliderfields/portlet/__init__.py
collective/sliderfields/portlet/configure.zcml
collective/sliderfields/profiles/default/browserlayer.xml
collective/sliderfields/profiles/default/collective.sliderfields.marker.txt
collective/sliderfields/profiles/default/cssregistry.xml
collective/sliderfields/profiles/default/jsregistry.xml
collective/sliderfields/profiles/default/metadata.xml
collective/sliderfields/profiles/default/portlets.xml
collective/sliderfields/profiles/default/types.xml
collective/sliderfields/schemaextender/__init__.py
collective/sliderfields/schemaextender/slider_image.py
collective/sliderfields/static/README.txt
collective/sliderfields/upgrades/__init__.py
collective/sliderfields/upgrades/handlers.py
collective/sliderfields/upgrades/profiles.py
collective/sliderfields/viewlet/__init__.py
collective/sliderfields/vocabulary/__init__.py
docs/HISTORY.rst
docs/INSTALL.rst
docs/LICENSE.GPL
docs/LICENSE.txt