Metadata-Version: 1.1
Name: collective.sliderfields
Version: 1.0
Summary: UNKNOWN
Home-page: http://github.com/inigoconsulting/
Author: Inigo Consulting
Author-email: team@inigo-tech.com
License: gpl
Platform: UNKNOWN
Classifier: Framework :: Plone
Classifier: Programming Language :: Python
Classifier: Topic :: Software Development :: Libraries :: Python Modules
